ncdlmuse/__about__.py
ncdlmuse/__init__.py
ncdlmuse/__main__.py
ncdlmuse/_version.py
ncdlmuse/_warnings.py
ncdlmuse/config.py
ncdlmuse/cli/__init__.py
ncdlmuse/cli/parser.py
ncdlmuse/cli/run.py
ncdlmuse/cli/version.py
ncdlmuse/cli/workflow.py
ncdlmuse/data/MUSE_ROI_complete_list.tsv
ncdlmuse/data/MUSE_mapping_consecutive_indices.json
ncdlmuse/data/MUSE_mapping_consecutive_indices.tsv
ncdlmuse/data/NOTICE
ncdlmuse/data/__init__.py
ncdlmuse/data/boilerplate.bib
ncdlmuse/data/io_spec.json
ncdlmuse/data/ncdlmuse_bids_config.json
ncdlmuse/data/paper_sample.yml
ncdlmuse/data/reports-spec.yml
ncdlmuse/data/reports/anat_report_template.tpl
ncdlmuse/interfaces/__init__.py
ncdlmuse/interfaces/bids.py
ncdlmuse/interfaces/ncdlmuse.py
ncdlmuse/interfaces/reports.py
ncdlmuse/interfaces/utility.py
ncdlmuse/reports/__init__.py
ncdlmuse/reports/individual.py
ncdlmuse/tests/__init__.py
ncdlmuse/tests/conftest.py
ncdlmuse/tests/run_local_tests.py
ncdlmuse/tests/test_cli.py
ncdlmuse/tests/test_interfaces.py
ncdlmuse/tests/test_parser.py
ncdlmuse/tests/test_version.py
ncdlmuse/tests/test_workflow.py
ncdlmuse/tests/utils.py
ncdlmuse/utils/__init__.py
ncdlmuse/utils/bids.py
ncdlmuse/utils/misc.py
ncdlmuse/workflows/__init__.py
ncdlmuse/workflows/base.py
ncdlmuse/workflows/group.py
ncdlmuse/workflows/ncdlmuse/__init__.py
ncdlmuse/workflows/ncdlmuse/ncdlmuse.py
ncdlmuse-0.1.4.dist-info/METADATA
ncdlmuse-0.1.4.dist-info/WHEEL
ncdlmuse-0.1.4.dist-info/entry_points.txt
ncdlmuse-0.1.4.dist-info/licenses/LICENSE.md
ncdlmuse-0.1.4.dist-info/RECORD
